sglang/__init__.py
sglang/bench_offline_throughput.py
sglang/bench_one_batch.py
sglang/bench_one_batch_server.py
sglang/bench_serving.py
sglang/check_env.py
sglang/compile_deep_gemm.py
sglang/global_config.py
sglang/launch_server.py
sglang/profiler.py
sglang/utils.py
sglang/version.py
sglang/eval/llama3_eval.py
sglang/eval/loogle_eval.py
sglang/lang/api.py
sglang/lang/chat_template.py
sglang/lang/choices.py
sglang/lang/compiler.py
sglang/lang/interpreter.py
sglang/lang/ir.py
sglang/lang/tracer.py
sglang/lang/backend/anthropic.py
sglang/lang/backend/base_backend.py
sglang/lang/backend/litellm.py
sglang/lang/backend/openai.py
sglang/lang/backend/runtime_endpoint.py
sglang/lang/backend/vertexai.py
sglang/srt/_custom_ops.py
sglang/srt/aio_rwlock.py
sglang/srt/bench_utils.py
sglang/srt/code_completion_parser.py
sglang/srt/constants.py
sglang/srt/conversation.py
sglang/srt/custom_op.py
sglang/srt/harmony_parser.py
sglang/srt/hf_transformers_utils.py
sglang/srt/host_shared_memory.py
sglang/srt/jinja_template_utils.py
sglang/srt/model_parallel.py
sglang/srt/offloader.py
sglang/srt/operations.py
sglang/srt/operations_strategy.py
sglang/srt/patch_torch.py
sglang/srt/poll_based_barrier.py
sglang/srt/reasoning_parser.py
sglang/srt/server_args.py
sglang/srt/torch_memory_saver_adapter.py
sglang/srt/two_batch_overlap.py
sglang/srt/utils.py
sglang/srt/warmup.py
sglang/srt/configs/__init__.py
sglang/srt/configs/chatglm.py
sglang/srt/configs/dbrx.py
sglang/srt/configs/deepseekvl2.py
sglang/srt/configs/device_config.py
sglang/srt/configs/exaone.py
sglang/srt/configs/internvl.py
sglang/srt/configs/janus_pro.py
sglang/srt/configs/kimi_vl.py
sglang/srt/configs/kimi_vl_moonvit.py
sglang/srt/configs/load_config.py
sglang/srt/configs/model_config.py
sglang/srt/configs/step3_vl.py
sglang/srt/configs/update_config.py
sglang/srt/configs/utils.py
sglang/srt/connector/__init__.py
sglang/srt/connector/base_connector.py
sglang/srt/connector/redis.py
sglang/srt/connector/s3.py
sglang_usf-0.5.1.post6.dist-info/licenses/LICENSE
sglang_usf-0.5.1.post6.dist-info/METADATA
sglang_usf-0.5.1.post6.dist-info/WHEEL
sglang_usf-0.5.1.post6.dist-info/top_level.txt
sglang_usf-0.5.1.post6.dist-info/RECORD
